stuff_package/__init__.py
stuff_package/stuff.py
example_pkg_stuff-0.0.1.dist-info/LICENSE
example_pkg_stuff-0.0.1.dist-info/METADATA
example_pkg_stuff-0.0.1.dist-info/WHEEL
example_pkg_stuff-0.0.1.dist-info/top_level.txt
example_pkg_stuff-0.0.1.dist-info/RECORD
